DogODay/__init__.py
DogODay/__main__.py
DogODay/app.py
DogODay/auth.py
DogODay/gui/__init__.py
DogODay/gui/controller.py
DogODay/gui/model.py
DogODay/gui/view.py
DogODay/res/config.json
DogODay/res/placeholder.png
DogODay-0.1.0.dist-info/LICENSE
DogODay-0.1.0.dist-info/METADATA
DogODay-0.1.0.dist-info/WHEEL
DogODay-0.1.0.dist-info/entry_points.txt
DogODay-0.1.0.dist-info/top_level.txt
DogODay-0.1.0.dist-info/RECORD
