Metadata-Version: 2.2
Name: DogODay
Version: 0.1.0
Summary: La app que te permitirá buscar por razas y votar por tus fotos favoritas del mejor amigo del hombre!
Author: Franklin Alvarez
Author-email: fyac44@gmail.com
License: GNU GLP
Classifier: Programming Language :: Python :: 3
Classifier: License :: OSI Approved :: GNU General Public License v3 or later (GPLv3+)
Classifier: Operating System :: OS Independent
Requires-Python: >=3.7
License-File: LICENSE
Requires-Dist: PyQt6>=6.8.0
Requires-Dist: requests>=2.25.0
